{
    "products": [

        {
            "id": "afed1342ha22pc",
            "name": "Black and white",
            "group": "Air Jordan 11",
            "available": true,
            "availableDate": "29/11",
            "gender": "Femme",
            "minSize": "35.5",
            "maxSize": "45.5",
            "price": "189,99",
            "baseSliderImageUrl": "https://images.stockx.com/360/Nike-Dunk-Low-Retro-White-Black-2021/Images/Nike-Dunk-Low-Retro-White-Black-2021/Lv2/img:index:.jpg?auto=compress&w=480&q=90&dpr=2&updated_at=1633027409&h=320&fm=webp",
            "description": "Adulée des joueurs et des amateurs de sneakers, la chaussure Air Jordan 11 Retro est confectionnée en cuir synthétique pour un confort optimal tout au long de la journée. Un cambrion en fibre de carbone offre une meilleure réactivité, tandis que l'unité Air Sole sur toute la longueur permet d'amortir votre foulée.",
            "descriptionImages": [
                "https://picsum.photos/300/300",
                "https://picsum.photos/300/300"
            ],
            "tags": [
                "air jordan",
                "jordan",
                "11",
                "femme"
            ]
        },

        {
            "id": "aefij42rag234aei",
            "name": "White",
            "group": "Kwondo1",
            "available": true,
            "availableDate": "29/11",
            "gender": "Homme",
            "minSize": "35.5",
            "maxSize": "49.5",
            "price": "179,99",
            "previewImages": [
                "https://picsum.photos/300/300",
                "https://picsum.photos/300/300",
                "https://picsum.photos/300/300"
            ],
            "description": "Prête pour la rue. Prête pour le tapis rouge. Prête pour la piste de danse. Tout droit sortie de l'imagination de G-Dragon, la Kwondo1 est conçue pour libérer un potentiel nouveau dans nos espaces préférés. Comment ? En exploitant notre liberté d'expression, notre créativité et notre audace sans limites. La Kwondo1, dont le nom est un mélange de « Kwon » et de « Just Do It », en référence à l'art martial traditionnel coréen du Tae-Kwon-do, représente une nouvelle toile vierge pour quiconque osera chausser cette toute nouvelle sneaker.",
            "descriptionImages": [
                "https://picsum.photos/300/300",
                "https://picsum.photos/300/300"
            ],
            "tags": [
                "kwondo",
                "kwondo1",
                "homme"
            ]
        }


    ]
}